flauncher/__init__.py
flauncher/__main__.py
flauncher/colors.py
flauncher/flauncher.py
flauncher/local.py
flauncher/log.py
flauncher/main.py
flauncher/__pycache__/__init__.cpython-37.pyc
flauncher/__pycache__/colors.cpython-37.pyc
flauncher/__pycache__/flauncher.cpython-37.pyc
flauncher/__pycache__/local.cpython-37.pyc
flauncher/__pycache__/log.cpython-37.pyc
flauncher/conf/README.md
flauncher/conf/edit.json
flauncher/conf/open.json
flauncher-1.5.0.dist-info/LICENSE
flauncher-1.5.0.dist-info/METADATA
flauncher-1.5.0.dist-info/WHEEL
flauncher-1.5.0.dist-info/entry_points.txt
flauncher-1.5.0.dist-info/top_level.txt
flauncher-1.5.0.dist-info/RECORD
