Metadata-Version: 2.1
Name: flauncher
Version: 1.5.0
Summary: Universal CLI file launcher
Home-page: https://github.com/yoarch/flauncher
Author: yoarch
Author-email: yo.managements@gmail.com
License: UNKNOWN
Platform: UNKNOWN
Classifier: Programming Language :: Python :: 3
Classifier: License :: OSI Approved :: MIT License
Classifier: Operating System :: OS Independent
Requires-Python: >=3
License-File: LICENSE
Requires-Dist: natsort
